plate_model_manager/__init__.py
plate_model_manager/__main__.py
plate_model_manager/auxiliary.py
plate_model_manager/exceptions.py
plate_model_manager/file_fetcher.py
plate_model_manager/network_aiohttp.py
plate_model_manager/network_requests.py
plate_model_manager/plate_model.py
plate_model_manager/plate_model_manager.py
plate_model_manager/present_day_rasters.py
plate_model_manager/zenodo.py
plate_model_manager/utils/download.py
plate_model_manager/utils/misc.py
plate_model_manager/utils/network.py
plate_model_manager/utils/unzip.py
plate_model_manager-1.3.1.dist-info/licenses/LICENSE
plate_model_manager-1.3.1.dist-info/METADATA
plate_model_manager-1.3.1.dist-info/WHEEL
plate_model_manager-1.3.1.dist-info/entry_points.txt
plate_model_manager-1.3.1.dist-info/top_level.txt
plate_model_manager-1.3.1.dist-info/RECORD
