Metadata-Version: 2.4
Name: plate-model-manager
Version: 1.3.1
Summary: Plate Model Manager
Author-email: Michael Chin <michael.chin@sydney.edu.au>
License:                     GNU GENERAL PUBLIC LICENSE
Project-URL: Homepage, https://github.com/gplates/plate-model-manager
Keywords: Geoscience,Plate Tectonics,Earth,Geophysics
Classifier: License :: OSI Approved :: GNU General Public License v2 (GPLv2)
Classifier: Programming Language :: Python
Classifier: Programming Language :: Python :: 3
Classifier: Programming Language :: Python :: 3.9
Classifier: Programming Language :: Python :: 3.10
Classifier: Programming Language :: Python :: 3.11
Classifier: Programming Language :: Python :: 3.12
Classifier: Programming Language :: Python :: 3.13
Requires-Python: >=3.9
License-File: LICENSE
Requires-Dist: aiohttp
Requires-Dist: requests
Requires-Dist: nest_asyncio
Provides-Extra: dev
Requires-Dist: black; extra == "dev"
Requires-Dist: bumpver; extra == "dev"
Requires-Dist: isort; extra == "dev"
Requires-Dist: pip-tools; extra == "dev"
Requires-Dist: pytest; extra == "dev"
Dynamic: license-file
